setuptools_gopy/__init__.py
setuptools_gopy/_command.py
setuptools_gopy/cmd_build.py
setuptools_gopy/docker.py
setuptools_gopy/extension.py
setuptools_gopy/flags.py
setuptools_gopy/go.py
setuptools_gopy/py.typed
setuptools_gopy/setuptools_ext.py
setuptools_gopy/utils.py
setuptools_gopy-0.0.9.dist-info/METADATA
setuptools_gopy-0.0.9.dist-info/WHEEL
setuptools_gopy-0.0.9.dist-info/entry_points.txt
setuptools_gopy-0.0.9.dist-info/top_level.txt
setuptools_gopy-0.0.9.dist-info/zip-safe
setuptools_gopy-0.0.9.dist-info/RECORD
