Metadata-Version: 2.4
Name: setuptools-gopy
Version: 0.0.9
Summary: Setuptools Gopy extension plugin
Author-email: Louis Brunner <pip@lbrunner.net>
License-Expression: MPL-2.0
Project-URL: Homepage, https://github.com/LouisBrunner/setuptools-gopy
Project-URL: Repository, https://github.com/LouisBrunner/setuptools-gopy
Keywords: distutils,setuptools,go,golang
Classifier: Intended Audience :: Developers
Classifier: Programming Language :: Python :: 3
Classifier: Development Status :: 3 - Alpha
Classifier: Operating System :: OS Independent
Requires-Python: >=3.13
Requires-Dist: setuptools>=62.4
Requires-Dist: pybindgen==0.22.1
